macula/__about__.py
macula/__init__.py
macula/geometry/__init__.py
macula/geometry/frame.py
macula/geometry/primitives.py
tests/__init__.py
macula-0.0.5.dist-info/LICENSE
macula-0.0.5.dist-info/METADATA
macula-0.0.5.dist-info/WHEEL
macula-0.0.5.dist-info/top_level.txt
macula-0.0.5.dist-info/RECORD
