Metadata-Version: 2.1
Name: macula
Version: 0.0.5
Summary: Library for creative software design and development
Author: Daan Rongen
Author-email: <hi@daan.website>
Keywords: python
Classifier: Development Status :: 1 - Planning
Classifier: Intended Audience :: Developers
Classifier: Programming Language :: Python :: 3
Classifier: Operating System :: Unix
Classifier: Operating System :: MacOS :: MacOS X
Classifier: Operating System :: Microsoft :: Windows
License-File: LICENSE
